{
  "plot": "Jan (Daniel Br\u00fchl), Peter (Stipe Erceg) und Jule (Julia Jentsch) wollen eigentlich nur ein bisschen gegen die Ungerechtigkeit der Welt rebellieren und den Pfeffers\u00e4cken im Villenviertel einen Denkzettel verpassen. Deshalb steigen sie bei Nacht- und Nebelaktionen in die H\u00e4user ein. Doch statt zu stehlen verr\u00fccken sie die M\u00f6bel und veranstalten Streiche. Als sie bei einem ihrer Streifz\u00fcge pl\u00f6tzlich von dem Topmanager Hardenberg (Burghart Klau\u00dfner) \u00fcberrascht werden, droht aus Spa\u00df krimineller Ernst zu werden.", 
  "thumbnails": [
    "http://d3gtl9l2a4fn1j.cloudfront.net/t/p/w500/8JeST4whGuP2O40qVzO694g2jKi.jpg", 
    "http://d3gtl9l2a4fn1j.cloudfront.net/t/p/w500/aTJT2ZHDMOHPPKCDPWyg19CUaP2.jpg", 
    "http://d3gtl9l2a4fn1j.cloudfront.net/t/p/w500/r0mJOWL4jVkTXcvfVvYj7JhEDMV.jpg", 
    "http://d3gtl9l2a4fn1j.cloudfront.net/t/p/w500/FbuI3mLvyB3pSruT2khkSWe5JY.jpg", 
    "http://d3gtl9l2a4fn1j.cloudfront.net/t/p/w500/gdSWonhqOEIzhx6tU2iCABQ9xBi.jpg", 
    "http://d3gtl9l2a4fn1j.cloudfront.net/t/p/w500/xlp9TGtpwChoyraWUUaJElypkFY.jpg"
  ], 
  "rating": "7.4", 
  "fanart": [
    "http://d3gtl9l2a4fn1j.cloudfront.net/t/p/w780/dhW2C8AX8IwHgfupCksL47tppwp.jpg"
  ], 
  "mpaa": "Rated 12", 
  "youtube_id": "UyT8bEa4XYA", 
  "title_original": "Die fetten Jahre sind vorbei", 
  "country": "Austria", 
  "director": "Hans Weingartner", 
  "writers": "Hans Weingartner / Katharina Held", 
  "studio": "Y3 Film", 
  "title_local": "Die fetten Jahre sind vorbei", 
  "imdb_id": "tt0408777", 
  "year": "2004", 
  "genre": "Kom\u00f6die / Drama / Foreign", 
  "date_added": "2012-10-19", 
  "runtime": "127", 
  "rating_votes": "21.686", 
  "plot_outline": ""
}